LICENSE.txt
MANIFEST.in
README.rst
RELEASE_NOTES.rst
setup.cfg
setup.py
rclickatell/__init__.py
rclickatell/admin.py
rclickatell/app.py
rclickatell/backend.py
rclickatell/forms.py
rclickatell/models.py
rclickatell/tests.py
rclickatell/urls.py
rclickatell/views.py
rclickatell.egg-info/PKG-INFO
rclickatell.egg-info/SOURCES.txt
rclickatell.egg-info/dependency_links.txt
rclickatell.egg-info/requires.txt
rclickatell.egg-info/top_level.txt